PHASE/__init__.py
PHASE/dataset.py
PHASE/main.py
PHASE/modules.py
PHASE/utils.py
phase_sc-2.0.4.dist-info/LICENSE
phase_sc-2.0.4.dist-info/METADATA
phase_sc-2.0.4.dist-info/WHEEL
phase_sc-2.0.4.dist-info/entry_points.txt
phase_sc-2.0.4.dist-info/top_level.txt
phase_sc-2.0.4.dist-info/RECORD
