Metadata-Version: 2.1
Name: phase-sc
Version: 2.0.4
Summary: PHASE:PHenotype prediction with Attention mechanisms for Single-cell Exploring
Home-page: https://github.com/wuqinhua/PHASE.git
Author: Qinhua Wu
Author-email: wuqinhua21@mails.ucas.ac.cn
Classifier: Programming Language :: Python :: 3
Classifier: License :: OSI Approved :: MIT License
Classifier: Operating System :: OS Independent
Requires-Python: >=3.10
License-File: LICENSE
